[{"name":"Accra","locationParts":["Accra"],"countryCode":"gh","country":"Ghana"},{"name":"Anloga","locationParts":["Anloga"],"countryCode":"gh","country":"Ghana"},{"name":"Apam","locationParts":["Apam"],"countryCode":"gh","country":"Ghana"},{"name":"Axim","locationParts":["Axim"],"countryCode":"gh","country":"Ghana"},{"name":"Cape Coast","locationParts":["Cape","Coast"],"countryCode":"gh","country":"Ghana"},{"name":"Elmina","locationParts":["Elmina"],"countryCode":"gh","country":"Ghana"},{"name":"Keta","locationParts":["Keta"],"countryCode":"gh","country":"Ghana"},{"name":"Nungua","locationParts":["Nungua"],"countryCode":"gh","country":"Ghana"},{"name":"Saltpond","locationParts":["Saltpond"],"countryCode":"gh","country":"Ghana"},{"name":"Sekondi","locationParts":["Sekondi"],"countryCode":"gh","country":"Ghana"},{"name":"Shama Junction","locationParts":["Shama","Junction"],"countryCode":"gh","country":"Ghana"},{"name":"Takoradi","locationParts":["Takoradi","Ghana"],"countryCode":"gh","country":"Ghana"},{"name":"Teshi","locationParts":["Teshi"],"countryCode":"gh","country":"Ghana"}]