[{"name":"Barranca","locationParts":["Barranca"],"countryCode":"pe","country":"Peru"},{"name":"Callao","locationParts":["Callao","Peru"],"countryCode":"pe","country":"Peru"},{"name":"Camana","locationParts":["Camana"],"countryCode":"pe","country":"Peru"},{"name":"Chancay","locationParts":["Chancay"],"countryCode":"pe","country":"Peru"},{"name":"Chilca","locationParts":["Chilca"],"countryCode":"pe","country":"Peru"},{"name":"Chimbote","locationParts":["Chimbote"],"countryCode":"pe","country":"Peru"},{"name":"Coishco","locationParts":["Coishco"],"countryCode":"pe","country":"Peru"},{"name":"Eten","locationParts":["Eten"],"countryCode":"pe","country":"Peru"},{"name":"Huacho","locationParts":["Huacho"],"countryCode":"pe","country":"Peru"},{"name":"Hualmay","locationParts":["Hualmay"],"countryCode":"pe","country":"Peru"},{"name":"Huarmey","locationParts":["Huarmey"],"countryCode":"pe","country":"Peru"},{"name":"Huaura","locationParts":["Huaura"],"countryCode":"pe","country":"Peru"},{"name":"Ilo","locationParts":["Ilo"],"countryCode":"pe","country":"Peru"},{"name":"Lima","locationParts":["Lima"],"countryCode":"pe","country":"Peru"},{"name":"Mala","locationParts":["Mala","1"],"countryCode":"pe","country":"Peru"},{"name":"Mancora","locationParts":["Mancora"],"countryCode":"pe","country":"Peru"},{"name":"Matarani","locationParts":["Matarani","Peru"],"countryCode":"pe","country":"Peru"},{"name":"Moche","locationParts":["Moche"],"countryCode":"pe","country":"Peru"},{"name":"Mollendo","locationParts":["Mollendo"],"countryCode":"pe","country":"Peru"},{"name":"Monsefu","locationParts":["Monsefu"],"countryCode":"pe","country":"Peru"},{"name":"Pacasmayo","locationParts":["Pacasmayo"],"countryCode":"pe","country":"Peru"},{"name":"Pacocha","locationParts":["Pacocha"],"countryCode":"pe","country":"Peru"},{"name":"Paita","locationParts":["Paita"],"countryCode":"pe","country":"Peru"},{"name":"Paramonga","locationParts":["Paramonga"],"countryCode":"pe","country":"Peru"},{"name":"Pativilca","locationParts":["Pativilca"],"countryCode":"pe","country":"Peru"},{"name":"Pimentel","locationParts":["Pimentel"],"countryCode":"pe","country":"Peru"},{"name":"Pisco","locationParts":["Pisco"],"countryCode":"pe","country":"Peru"},{"name":"Puerto Santa","locationParts":["Puerto","Santa"],"countryCode":"pe","country":"Peru"},{"name":"Puerto Supe","locationParts":["Puerto","Supe"],"countryCode":"pe","country":"Peru"},{"name":"Punta de Bombon","locationParts":["Punta","de","Bombon"],"countryCode":"pe","country":"Peru"},{"name":"Salaverry","locationParts":["Salaverry"],"countryCode":"pe","country":"Peru"},{"name":"Salinera Colan","locationParts":["Salinera","Colan"],"countryCode":"pe","country":"Peru"},{"name":"San Bartolo","locationParts":["San","Bartolo","1"],"countryCode":"pe","country":"Peru"},{"name":"Santiago de Cao","locationParts":["Santiago","de","Cao"],"countryCode":"pe","country":"Peru"},{"name":"Supe","locationParts":["Supe"],"countryCode":"pe","country":"Peru"},{"name":"Talara","locationParts":["Talara","Peru"],"countryCode":"pe","country":"Peru"},{"name":"Trujillo","locationParts":["Trujillo"],"countryCode":"pe","country":"Peru"},{"name":"Tumbes","locationParts":["Tumbes"],"countryCode":"pe","country":"Peru"},{"name":"Vegueta","locationParts":["Vegueta"],"countryCode":"pe","country":"Peru"},{"name":"Zorritos","locationParts":["Zorritos"],"countryCode":"pe","country":"Peru"}]